bedrock_tracing/__init__.py
bedrock_tracing/tracing.py
bedrock_tracing-0.5.0.dist-info/LICENSE
bedrock_tracing-0.5.0.dist-info/METADATA
bedrock_tracing-0.5.0.dist-info/WHEEL
bedrock_tracing-0.5.0.dist-info/top_level.txt
bedrock_tracing-0.5.0.dist-info/RECORD
