Metadata-Version: 2.1
Name: bedrock-tracing
Version: 0.5.0
Summary: A Python library for tracing Bedrock agent responses with OpenTelemetry.
Home-page: https://github.com/agithomas/bedrock-tracing
Author: Agi K Thomas
Author-email: agikthomas@hotmail.com
Classifier: Programming Language :: Python :: 3
Classifier: License :: OSI Approved :: MIT License
Classifier: Operating System :: OS Independent
Requires-Python: >=3.7
License-File: LICENSE
Requires-Dist: opentelemetry-api
Requires-Dist: opentelemetry-sdk
